node.ext.zodb-1.6-nspkg.pth
node/ext/zodb/__init__.py
node/ext/zodb/behaviors.py
node/ext/zodb/interfaces.py
node/ext/zodb/tests.py
node/ext/zodb/utils.py
node.ext.zodb-1.6.dist-info/LICENSE.rst
node.ext.zodb-1.6.dist-info/METADATA
node.ext.zodb-1.6.dist-info/WHEEL
node.ext.zodb-1.6.dist-info/namespace_packages.txt
node.ext.zodb-1.6.dist-info/top_level.txt
node.ext.zodb-1.6.dist-info/RECORD
